zc.recipe.filestorage-2.0-py3.9-nspkg.pth
zc/recipe/filestorage/README.rst
zc/recipe/filestorage/__init__.py
zc/recipe/filestorage/tests.py
zc.recipe.filestorage-2.0.dist-info/LICENSE.txt
zc.recipe.filestorage-2.0.dist-info/METADATA
zc.recipe.filestorage-2.0.dist-info/WHEEL
zc.recipe.filestorage-2.0.dist-info/entry_points.txt
zc.recipe.filestorage-2.0.dist-info/namespace_packages.txt
zc.recipe.filestorage-2.0.dist-info/top_level.txt
zc.recipe.filestorage-2.0.dist-info/zip-safe
zc.recipe.filestorage-2.0.dist-info/RECORD
