Metadata-Version: 2.1
Name: zc.recipe.filestorage
Version: 2.0
Summary: ZC Buildout recipe for defining a file-storage
Home-page: https://pypi.org/project/zc.recipe.filestorage/
Author: Jim Fulton
Author-email: zope-dev@zope.dev
License: ZPL 2.1
Keywords: zodb,zc.buildout
Classifier: Development Status :: 5 - Production/Stable
Classifier: Framework :: ZODB
Classifier: Framework :: Buildout
Classifier: Intended Audience :: Developers
Classifier: License :: OSI Approved :: Zope Public License
Classifier: Topic :: Software Development :: Build Tools
Classifier: Topic :: Software Development :: Libraries :: Python Modules
Classifier: Natural Language :: English
Classifier: Programming Language :: Python
Classifier: Programming Language :: Python :: 3
Classifier: Programming Language :: Python :: 3.7
Classifier: Programming Language :: Python :: 3.8
Classifier: Programming Language :: Python :: 3.9
Classifier: Programming Language :: Python :: 3.10
Classifier: Programming Language :: Python :: 3.11
Classifier: Programming Language :: Python :: Implementation :: CPython
Classifier: Programming Language :: Python :: Implementation :: PyPy
Requires-Python: >=3.7
License-File: LICENSE.txt
Requires-Dist: zc.buildout
Requires-Dist: zope.testing
Requires-Dist: setuptools
